pyrsona/__init__.py
pyrsona-1.1.dist-info/LICENSE
pyrsona-1.1.dist-info/METADATA
pyrsona-1.1.dist-info/WHEEL
pyrsona-1.1.dist-info/RECORD
