Metadata-Version: 2.3
Name: pyrsona
Version: 1.1
Summary: 
License: MIT
Author: John
Author-email: johnbullnz@gmail.com
Requires-Python: >=3.9,<4.0
Classifier: License :: OSI Approved :: MIT License
Classifier: Programming Language :: Python :: 3
Classifier: Programming Language :: Python :: 3.9
Classifier: Programming Language :: Python :: 3.10
Classifier: Programming Language :: Python :: 3.11
Classifier: Programming Language :: Python :: 3.12
Classifier: Programming Language :: Python :: 3.13
Requires-Dist: numpy (>=1.22.2,<2.0.0)
Requires-Dist: parse (>=1.19.0,<2.0.0)
Requires-Dist: psutil (>=5.9.0,<6.0.0)
Requires-Dist: pydantic (>=2,<3)
Requires-Dist: unsync (>=1.4.0,<2.0.0)
Project-URL: Homepage, https://github.com/johnbullnz/pyrsona
